{
  "playerPosition": [
      { "x": 0,  "y": 0 },
      { "x": -3, "y": 1 },
      { "x": 3, "y": 1 },
      { "x": -3, "y": 2 },
      { "x": 3, "y": 2 }
  ],
  "cardPosition": [
      [
          { "x": 0, "y": 0 },
          { "x": 0.2, "y": 0 },
          { "x": 0.4, "y": 0 },
          { "x": 0.6000000000000001, "y": 0 }
      ],
      [
          { "x": -2.96, "y": 1 },
          { "x": -2.76, "y": 1 },
          { "x": -2.56, "y": 1 },
          { "x": -2.36, "y": 1 }
      ],
      [
          { "x": 3.08, "y": 1 },
          { "x": 3.28, "y": 1 },
          { "x": 3.48, "y": 1 },
          { "x": 3.68, "y": 1 }
      ],
      [
          { "x": -2.88, "y": 2 },
          { "x": -2.6799999999999997, "y": 2 },
          { "x": -2.48, "y": 2 },
          { "x": -2.28, "y": 2 }
      ],
      [
          { "x": 3.16, "y": 2 },
          { "x": 3.36, "y": 2 },
          { "x": 3.56, "y": 2 },
          { "x": 3.76, "y": 2 }
      ]
  ],
  "enemyDeck": [
      {
          "suit": "joker",
          "value": "joker"
      },
      {
          "suit": "joker",
          "value": "joker"
      },
      {
          "suit": "joker",
          "value": "joker"
      },
      {
          "suit": "joker",
          "value": "joker"
      }
  ]
}